cai2/CAI.py
cai2/__init__.py
cai2/cli.py
cai2-1.0.5.dist-info/METADATA
cai2-1.0.5.dist-info/LICENSE.txt
cai2-1.0.5.dist-info/WHEEL
cai2-1.0.5.dist-info/RECORD
