Metadata-Version: 2.1
Name: cai2
Version: 1.0.5
Summary: Python implementation of codon adaptation index
License: MIT
Author: Benjamin Lee
Author-email: benjamin_lee@college.harvard.edu
Requires-Python: >=3.8
Classifier: License :: OSI Approved :: MIT License
Classifier: Programming Language :: Python :: 3
Classifier: Programming Language :: Python :: 3.8
Classifier: Programming Language :: Python :: 3.9
Classifier: Programming Language :: Python :: 3.10
Classifier: Programming Language :: Python :: 3.11
Requires-Dist: biopython (>=1.80)
Requires-Dist: click (>=7)
Requires-Dist: scipy
